quercle_pydantic_ai/__init__.py
quercle_pydantic_ai/py.typed
quercle_pydantic_ai/tools.py
quercle_pydantic_ai-0.1.0.dist-info/METADATA
quercle_pydantic_ai-0.1.0.dist-info/WHEEL
quercle_pydantic_ai-0.1.0.dist-info/licenses/LICENSE
quercle_pydantic_ai-0.1.0.dist-info/RECORD
