Metadata-Version: 2.4
Name: quercle-pydantic-ai
Version: 0.1.0
Summary: Quercle web search and URL fetch tools for Pydantic AI agents
Project-URL: Homepage, https://github.com/quercledev/quercle-pydantic-ai
Project-URL: Documentation, https://quercle.dev/docs
Project-URL: Repository, https://github.com/quercledev/quercle-pydantic-ai
Author-email: Quercle <support@quercle.dev>
License-Expression: MIT
License-File: LICENSE
Keywords: agents,ai,llm,pydantic-ai,quercle,tools,web-search
Classifier: Development Status :: 4 - Beta
Classifier: Intended Audience :: Developers
Classifier: License :: OSI Approved :: MIT License
Classifier: Programming Language :: Python :: 3
Classifier: Programming Language :: Python :: 3.10
Classifier: Programming Language :: Python :: 3.11
Classifier: Programming Language :: Python :: 3.12
Classifier: Programming Language :: Python :: 3.13
Classifier: Topic :: Scientific/Engineering :: Artificial Intelligence
Requires-Python: >=3.10
Requires-Dist: pydantic-ai>=0.1.0
Requires-Dist: quercle>=0.1.3
Provides-Extra: dev
Requires-Dist: pytest-asyncio>=0.24; extra == 'dev'
Requires-Dist: pytest>=8.0; extra == 'dev'
Requires-Dist: ruff>=0.8; extra == 'dev'
Requires-Dist: ty; extra == 'dev'
